gitlabci_checker/__init__.py
gitlabci_checker/cli.py
gitlabci_checker/helpers.py
gitlabci_checker-0.1.3.dist-info/LICENSE
gitlabci_checker-0.1.3.dist-info/METADATA
gitlabci_checker-0.1.3.dist-info/WHEEL
gitlabci_checker-0.1.3.dist-info/entry_points.txt
gitlabci_checker-0.1.3.dist-info/RECORD
