Metadata-Version: 2.1
Name: gitlabci-checker
Version: 0.1.3
Summary: Checks if your gitlab-ci pipeline compiles correctly.
Home-page: https://github.com/lorenzophys/gitlabci-checker
Keywords: gitlab,ci,pipeline
Author: Lorenzo Maffioli
Author-email: lorenzo.maffioli@gmail.com
Requires-Python: >=3.9,<4.0
Classifier: Programming Language :: Python :: 3
Classifier: Programming Language :: Python :: 3.9
Classifier: Programming Language :: Python :: 3.10
Classifier: Programming Language :: Python :: 3.11
Classifier: Programming Language :: Python :: 3.12
Requires-Dist: click (>=8.1.3,<9.0.0)
Requires-Dist: requests (>=2.28.1,<3.0.0)
Requires-Dist: tox-poetry (>=0.5.0,<0.6.0)
Project-URL: Repository, https://github.com/lorenzophys/gitlabci-checker
